{
  "project_info": {
    "project_number": "31713907566",
    "project_id": "loginapp-6d1bf",
    "storage_bucket": "loginapp-6d1bf.appspot.com"
  },
  "client": [
    {
      "client_info": {
        "mobilesdk_app_id": "1:31713907566:android:6b5e46af1aa444c317677f",
        "android_client_info": {
          "package_name": "com.example.loginapp"
        }
      },
      "oauth_client": [
        {
          "client_id": "31713907566-ogic48o0vojnls8ju8k0evtenf2ohbq0.apps.googleusercontent.com",
          "client_type": 3
        }
      ],
      "api_key": [
        {
          "current_key": "AIzaSyBbxRVRIYHUIToBBRsoRMybW-O6jGg170I"
        }
      ],
      "services": {
        "appinvite_service": {
          "other_platform_oauth_client": [
            {
              "client_id": "31713907566-ogic48o0vojnls8ju8k0evtenf2ohbq0.apps.googleusercontent.com",
              "client_type": 3
            }
          ]
        }
      }
    }
  ],
  "configuration_version": "1"
}